subredo/__init__.py
subredo/helpers.py
subredo/main.py
subredo/timecode.py
subredo/timestamp.py
subredo/videoredocom.py
subredo/videoredoproject.py
subredo-1.1.0.dist-info/LICENSE
subredo-1.1.0.dist-info/METADATA
subredo-1.1.0.dist-info/WHEEL
subredo-1.1.0.dist-info/entry_points.txt
subredo-1.1.0.dist-info/RECORD
