Metadata-Version: 2.1
Name: subredo
Version: 1.1.0
Summary: Apply Cuts from VideoReDo Project Files to Subtitles.
Home-page: https://github.com/rlaphoenix/SubReDo
Keywords: python,subtitles,cut,editor
Author: rlaphoenix
Author-email: rlaphoenix@pm.me
Requires-Python: >=3.7,<3.12
Classifier: Development Status :: 4 - Beta
Classifier: Intended Audience :: End Users/Desktop
Classifier: Natural Language :: English
Classifier: Operating System :: OS Independent
Classifier: Programming Language :: Python :: 3
Classifier: Programming Language :: Python :: 3.7
Classifier: Programming Language :: Python :: 3.8
Classifier: Programming Language :: Python :: 3.9
Classifier: Programming Language :: Python :: 3.10
Classifier: Programming Language :: Python :: 3.11
Classifier: Topic :: Multimedia
Classifier: Topic :: Multimedia :: Video
Classifier: Topic :: Utilities
Requires-Dist: click (>=8.1.3,<9.0.0)
Requires-Dist: comtypes (>=1.2.0,<2.0.0) ; sys_platform == "win32"
Requires-Dist: pymediainfo (>=6.0.1,<7.0.0)
Requires-Dist: pywin32 (>=306,<307) ; sys_platform == "win32"
Requires-Dist: rich (>=13.3.4,<14.0.0)
Project-URL: Bug Tracker, https://github.com/rlaphoenix/SubReDo/issues
Project-URL: Changelog, https://github.com/rlaphoenix/SubReDo/blob/master/CHANGELOG.md
Project-URL: Forums, https://github.com/rlaphoenix/SubReDo/discussions
Project-URL: Repository, https://github.com/rlaphoenix/SubReDo
